jptest/JPFixture.py
jptest/JPTest.py
jptest/JPTestBook.py
jptest/JPTestCell.py
jptest/JPTestParams.py
jptest/RunTest.py
jptest/__init__.py
jptest/__main__.py
jptest-0.8.5.dist-info/LICENSE
jptest-0.8.5.dist-info/METADATA
jptest-0.8.5.dist-info/WHEEL
jptest-0.8.5.dist-info/top_level.txt
jptest-0.8.5.dist-info/RECORD
