Metadata-Version: 2.1
Name: jptest
Version: 0.8.5
Summary: write graded unit tests for Jupyter Notebooks in a few lines of code
Home-page: https://github.com/erictroebs/jptest
Author: Eric Tröbs
Author-email: eric.troebs@tu-ilmenau.de
Project-URL: Bug Tracker, https://github.com/erictroebs/jptest/issues
Classifier: Programming Language :: Python :: 3
Classifier: License :: OSI Approved :: MIT License
Classifier: Operating System :: OS Independent
Requires-Python: >=3.6
License-File: LICENSE
Requires-Dist: jupyter
Requires-Dist: testbook (~=0.4.2)
